pyrasfile/__init__.py
pyrasfile/csvReader.py
pyrasfile/main.py
pyrasfile/profileWriter.py
pyrasfile/reportReader.py
pyrasfile/utils.py
pyrasfile-1.0.0.dist-info/LICENSE
pyrasfile-1.0.0.dist-info/METADATA
pyrasfile-1.0.0.dist-info/WHEEL
pyrasfile-1.0.0.dist-info/top_level.txt
pyrasfile-1.0.0.dist-info/RECORD
