Metadata-Version: 2.1
Name: pyrasfile
Version: 1.0.0
Summary: A collection of HEC-RAS file writers and parsers
Home-page: https://github.com/larflows/pyrasfile
Author: Daniel Philippus
Author-email: dphilippus@protonmail.com
License: UNKNOWN
Platform: UNKNOWN
Classifier: Programming Language :: Python :: 3
Classifier: Operating System :: Microsoft :: Windows
Classifier: License :: OSI Approved :: GNU General Public License v3 (GPLv3)
